asyncoss/__init__.py
asyncoss/api.py
asyncoss/exceptions.py
asyncoss/http.py
asyncoss/iterators.py
asyncoss/models.py
asyncoss-0.0.4.dist-info/LICENSE
asyncoss-0.0.4.dist-info/METADATA
asyncoss-0.0.4.dist-info/WHEEL
asyncoss-0.0.4.dist-info/top_level.txt
asyncoss-0.0.4.dist-info/RECORD
