Metadata-Version: 2.1
Name: asyncoss
Version: 0.0.4
Summary: A async aliyun OSS library.
Home-page: UNKNOWN
Author: jerevia
Author-email: trilliondawn@gmail.com
License: MIT
Platform: UNKNOWN
Classifier: Development Status :: 4 - Beta
Classifier: Intended Audience :: Developers
Classifier: License :: OSI Approved :: MIT License
Classifier: Programming Language :: Python :: 3.6
Classifier: Programming Language :: Python :: 3.7
Requires-Dist: aiohttp
Requires-Dist: oss2
